metodos_numericos_dcb_fi/__init__.py
metodos_numericos_dcb_fi/data/__init__.py
metodos_numericos_dcb_fi/data/text_es.json
metodos_numericos_dcb_fi/utilidades/__init__.py
metodos_numericos_dcb_fi/utilidades/configuracion.py
metodos_numericos_dcb_fi/utilidades/extras.py
metodos_numericos_dcb_fi/utilidades/graficar.py
metodos_numericos_dcb_fi/utilidades/leerEntrada.py
metodos_numericos_dcb_fi/utilidades/mostrarResultados.py
metodos_numericos_dcb_fi/utilidades/validacion.py
metodos_numericos_dcb_fi-0.1.13.dist-info/LICENSE
metodos_numericos_dcb_fi-0.1.13.dist-info/METADATA
metodos_numericos_dcb_fi-0.1.13.dist-info/WHEEL
metodos_numericos_dcb_fi-0.1.13.dist-info/RECORD
