Metadata-Version: 2.1
Name: metodos-numericos-dcb-fi
Version: 0.1.13
Summary: Biblioteca con las utilidades necesarias para ejecutar los jupyter notebooks de métodos numéricos.
License: MIT
Author: Guillermo Hernandez Ruiz de Esparza
Author-email: guillermo.hre@gmail.com
Requires-Python: >=3.9
Classifier: License :: OSI Approved :: MIT License
Classifier: Programming Language :: Python :: 3
Classifier: Programming Language :: Python :: 3.9
Classifier: Programming Language :: Python :: 3.10
Classifier: Programming Language :: Python :: 3.11
Classifier: Programming Language :: Python :: 3.12
Requires-Dist: ipython (==8.18.1)
Requires-Dist: ipywidgets (==8.1.5)
Requires-Dist: nbformat (==5.9.2)
Requires-Dist: numpy (==1.26.4)
Requires-Dist: pandas (==2.2.1)
Requires-Dist: pathlib (==1.0.1)
Requires-Dist: plotly (==5.19.0)
Requires-Dist: scipy (==1.13.0)
Requires-Dist: sympy (==1.12)
Requires-Dist: typing (==3.7.4.3)
